<?xml version='1.0' encoding='UTF-8'?>
<tv>
  <channel id="Asianet News EPG Schedule &amp; Program Guide">
    <display-name>Asianet News EPG Schedule &amp; Program Guide</display-name>
  </channel>
  <programme start="18-02-2024 12:00AM(00:25:00)" channel="Asianet News EPG Schedule &amp; Program Guide">
    <title>Cover Story-</title>
  </programme>
  <programme start="18-02-2024 12:25AM(00:45:00)" channel="Asianet News EPG Schedule &amp; Program Guide">
    <title>News Hour-</title>
  </programme>
  <programme start="18-02-2024 01:10AM(00:05:00)" channel="Asianet News EPG Schedule &amp; Program Guide">
    <title>Dr. Aster-</title>
  </programme>
  <programme start="18-02-2024 01:15AM(00:25:00)" channel="Asianet News EPG Schedule &amp; Program Guide">
    <title>Poya Vaaram-</title>
  </programme>
  <programme start="18-02-2024 01:40AM(00:20:00)" channel="Asianet News EPG Schedule &amp; Program Guide">
    <title>Lokajalakam-</title>
  </programme>
  <programme start="18-02-2024 02:00AM(00:05:00)" channel="Asianet News EPG Schedule &amp; Program Guide">
    <title>Munshi-</title>
  </programme>
  <programme start="18-02-2024 02:05AM(00:25:00)" channel="Asianet News EPG Schedule &amp; Program Guide">
    <title>Gulf News-</title>
  </programme>
  <programme start="18-02-2024 02:30AM(00:25:00)" channel="Asianet News EPG Schedule &amp; Program Guide">
    <title>Vartha Neram-</title>
  </programme>
  <programme start="18-02-2024 02:55AM(00:25:00)" channel="Asianet News EPG Schedule &amp; Program Guide">
    <title>Kissan Krishideepam-</title>
  </programme>
  <programme start="18-02-2024 03:20AM(00:25:00)" channel="Asianet News EPG Schedule &amp; Program Guide">
    <title>Prapanchavum Manushinum-</title>
  </programme>
  <programme start="18-02-2024 03:45AM(00:25:00)" channel="Asianet News EPG Schedule &amp; Program Guide">
    <title>Nine @ 9-</title>
  </programme>
  <programme start="18-02-2024 04:10AM(00:25:00)" channel="Asianet News EPG Schedule &amp; Program Guide">
    <title>FIR Bulletin-</title>
  </programme>
  <programme start="18-02-2024 04:35AM(00:25:00)" channel="Asianet News EPG Schedule &amp; Program Guide">
    <title>Good Night News-</title>
  </programme>
  <programme start="18-02-2024 05:00AM(00:30:00)" channel="Asianet News EPG Schedule &amp; Program Guide">
    <title>News At 10-</title>
  </programme>
  <programme start="18-02-2024 05:30AM(00:25:00)" channel="Asianet News EPG Schedule &amp; Program Guide">
    <title>Gulf Round Up-</title>
  </programme>
  <programme start="18-02-2024 05:55AM(00:05:00)" channel="Asianet News EPG Schedule &amp; Program Guide">
    <title>Munshi-</title>
  </programme>
  <programme start="18-02-2024 06:00AM(00:25:00)" channel="Asianet News EPG Schedule &amp; Program Guide">
    <title>Asianet Varthakal-</title>
  </programme>
  <programme start="18-02-2024 06:25AM(00:05:00)" channel="Asianet News EPG Schedule &amp; Program Guide">
    <title>Body Guard-</title>
  </programme>
  <programme start="18-02-2024 06:30AM(00:30:00)" channel="Asianet News EPG Schedule &amp; Program Guide">
    <title>Asianet Varthakal-</title>
  </programme>
  <programme start="18-02-2024 07:00AM(00:30:00)" channel="Asianet News EPG Schedule &amp; Program Guide">
    <title>Namasthe Keralam-</title>
  </programme>
  <programme start="18-02-2024 07:30AM(00:30:00)" channel="Asianet News EPG Schedule &amp; Program Guide">
    <title>Innu Ethuvare-</title>
  </programme>
  <programme start="18-02-2024 08:00AM(00:15:00)" channel="Asianet News EPG Schedule &amp; Program Guide">
    <title>Innu Ethuvare-</title>
  </programme>
  <programme start="18-02-2024 08:15AM(00:15:00)" channel="Asianet News EPG Schedule &amp; Program Guide">
    <title>Sports News-</title>
  </programme>
  <programme start="18-02-2024 08:30AM(00:30:00)" channel="Asianet News EPG Schedule &amp; Program Guide">
    <title>Namasthe Keralam-</title>
  </programme>
  <programme start="18-02-2024 09:00AM(00:30:00)" channel="Asianet News EPG Schedule &amp; Program Guide">
    <title>Namasthe Keralam-</title>
  </programme>
  <programme start="18-02-2024 09:30AM(00:25:00)" channel="Asianet News EPG Schedule &amp; Program Guide">
    <title>Legent-</title>
  </programme>
  <programme start="18-02-2024 09:55AM(00:05:00)" channel="Asianet News EPG Schedule &amp; Program Guide">
    <title>Body Guard-</title>
  </programme>
  <programme start="18-02-2024 10:00AM(00:30:00)" channel="Asianet News EPG Schedule &amp; Program Guide">
    <title>Ippol Sambhavikkunnathu-</title>
  </programme>
  <programme start="18-02-2024 10:30AM(00:30:00)" channel="Asianet News EPG Schedule &amp; Program Guide">
    <title>Ippol Sambhavikkunnathu-</title>
  </programme>
  <programme start="18-02-2024 11:00AM(00:30:00)" channel="Asianet News EPG Schedule &amp; Program Guide">
    <title>Ippol Sambhavikkunnathu-</title>
  </programme>
  <programme start="18-02-2024 11:30AM(00:30:00)" channel="Asianet News EPG Schedule &amp; Program Guide">
    <title>Ippol Sambhavikkunnathu-</title>
  </programme>
  <programme start="18-02-2024 12:00PM(00:30:00)" channel="Asianet News EPG Schedule &amp; Program Guide">
    <title>Ippol Sambhavikkunnathu-</title>
  </programme>
  <programme start="18-02-2024 12:30PM(00:30:00)" channel="Asianet News EPG Schedule &amp; Program Guide">
    <title>Evo India-</title>
  </programme>
  <programme start="18-02-2024 01:00PM(00:30:00)" channel="Asianet News EPG Schedule &amp; Program Guide">
    <title>News @ 1-</title>
  </programme>
  <programme start="18-02-2024 01:30PM(00:25:00)" channel="Asianet News EPG Schedule &amp; Program Guide">
    <title>Chuttuvattaom-</title>
  </programme>
  <programme start="18-02-2024 01:55PM(00:05:00)" channel="Asianet News EPG Schedule &amp; Program Guide">
    <title>Dr. Aster-</title>
  </programme>
  <programme start="18-02-2024 02:00PM(00:30:00)" channel="Asianet News EPG Schedule &amp; Program Guide">
    <title>News @ 14-</title>
  </programme>
  <programme start="18-02-2024 02:30PM(00:30:00)" channel="Asianet News EPG Schedule &amp; Program Guide">
    <title>Yuvajanolsavam 2024-</title>
  </programme>
  <programme start="18-02-2024 03:00PM(00:30:00)" channel="Asianet News EPG Schedule &amp; Program Guide">
    <title>Asianet Varthakal-</title>
  </programme>
  <programme start="18-02-2024 03:30PM(00:25:00)" channel="Asianet News EPG Schedule &amp; Program Guide">
    <title>Vallathoru Kadha-</title>
  </programme>
  <programme start="18-02-2024 03:55PM(00:05:00)" channel="Asianet News EPG Schedule &amp; Program Guide">
    <title>Body Guard-</title>
  </programme>
  <programme start="18-02-2024 04:00PM(00:30:00)" channel="Asianet News EPG Schedule &amp; Program Guide">
    <title>News At 4 PM-</title>
  </programme>
  <programme start="18-02-2024 04:30PM(00:30:00)" channel="Asianet News EPG Schedule &amp; Program Guide">
    <title>Nava Keralam-</title>
  </programme>
  <programme start="18-02-2024 05:00PM(00:30:00)" channel="Asianet News EPG Schedule &amp; Program Guide">
    <title>Chuttuvattaom-</title>
  </programme>
  <programme start="18-02-2024 05:30PM(00:25:00)" channel="Asianet News EPG Schedule &amp; Program Guide">
    <title>Yuvajanolsavam 2024-</title>
  </programme>
  <programme start="18-02-2024 05:55PM(00:05:00)" channel="Asianet News EPG Schedule &amp; Program Guide">
    <title>Munshi-</title>
  </programme>
  <programme start="18-02-2024 06:00PM(00:30:00)" channel="Asianet News EPG Schedule &amp; Program Guide">
    <title>News Time-</title>
  </programme>
  <programme start="18-02-2024 06:30PM(00:30:00)" channel="Asianet News EPG Schedule &amp; Program Guide">
    <title>Naam Munnottu-</title>
  </programme>
  <programme start="18-02-2024 07:00PM(00:30:00)" channel="Asianet News EPG Schedule &amp; Program Guide">
    <title>Vartha Neram-</title>
  </programme>
  <programme start="18-02-2024 07:30PM(00:30:00)" channel="Asianet News EPG Schedule &amp; Program Guide">
    <title>Vartha Neram-</title>
  </programme>
  <programme start="18-02-2024 08:00PM(00:30:00)" channel="Asianet News EPG Schedule &amp; Program Guide">
    <title>News Hour Debate-</title>
  </programme>
  <programme start="18-02-2024 08:30PM(00:25:00)" channel="Asianet News EPG Schedule &amp; Program Guide">
    <title>News Hour Debate-</title>
  </programme>
  <programme start="18-02-2024 08:55PM(00:05:00)" channel="Asianet News EPG Schedule &amp; Program Guide">
    <title>Body Guard-</title>
  </programme>
  <programme start="18-02-2024 09:00PM(00:30:00)" channel="Asianet News EPG Schedule &amp; Program Guide">
    <title>Nine @ 9-</title>
  </programme>
  <programme start="18-02-2024 09:30PM(00:25:00)" channel="Asianet News EPG Schedule &amp; Program Guide">
    <title>Nerkkuner-</title>
  </programme>
  <programme start="18-02-2024 09:55PM(00:05:00)" channel="Asianet News EPG Schedule &amp; Program Guide">
    <title>Munshi-</title>
  </programme>
  <programme start="18-02-2024 10:00PM(00:30:00)" channel="Asianet News EPG Schedule &amp; Program Guide">
    <title>News At 10-</title>
  </programme>
  <programme start="18-02-2024 10:30PM(00:25:00)" channel="Asianet News EPG Schedule &amp; Program Guide">
    <title>FIR Bulletin-</title>
  </programme>
  <programme start="18-02-2024 10:55PM(00:05:00)" channel="Asianet News EPG Schedule &amp; Program Guide">
    <title>Body Guard-</title>
  </programme>
  <programme start="18-02-2024 11:00PM(00:30:00)" channel="Asianet News EPG Schedule &amp; Program Guide">
    <title>Good Night News-</title>
  </programme>
  <programme start="18-02-2024 11:30PM(00:25:00)" channel="Asianet News EPG Schedule &amp; Program Guide">
    <title>Gulf News-</title>
  </programme>
  <programme start="18-02-2024 11:55PM(00:05:00)" channel="Asianet News EPG Schedule &amp; Program Guide">
    <title>Munshi-</title>
  </programme>
  <programme start="19-02-2024 12:00AM(00:25:00)" channel="Asianet News EPG Schedule &amp; Program Guide">
    <title>Nerkkuner-</title>
  </programme>
  <programme start="19-02-2024 12:25AM(00:45:00)" channel="Asianet News EPG Schedule &amp; Program Guide">
    <title>News Hour-</title>
  </programme>
  <programme start="19-02-2024 01:10AM(00:05:00)" channel="Asianet News EPG Schedule &amp; Program Guide">
    <title>Dr. Aster-</title>
  </programme>
  <programme start="19-02-2024 01:15AM(00:25:00)" channel="Asianet News EPG Schedule &amp; Program Guide">
    <title>Kissan Krishideepam-</title>
  </programme>
  <programme start="19-02-2024 01:40AM(00:20:00)" channel="Asianet News EPG Schedule &amp; Program Guide">
    <title>Dream Home-</title>
  </programme>
  <programme start="19-02-2024 02:00AM(00:05:00)" channel="Asianet News EPG Schedule &amp; Program Guide">
    <title>Munshi-</title>
  </programme>
  <programme start="19-02-2024 02:05AM(00:25:00)" channel="Asianet News EPG Schedule &amp; Program Guide">
    <title>Gulf News-</title>
  </programme>
  <programme start="19-02-2024 02:30AM(00:25:00)" channel="Asianet News EPG Schedule &amp; Program Guide">
    <title>Vartha Neram-</title>
  </programme>
  <programme start="19-02-2024 02:55AM(00:25:00)" channel="Asianet News EPG Schedule &amp; Program Guide">
    <title>Point Blank-</title>
  </programme>
  <programme start="19-02-2024 03:20AM(00:25:00)" channel="Asianet News EPG Schedule &amp; Program Guide">
    <title>Poya Vaaram-</title>
  </programme>
  <programme start="19-02-2024 03:45AM(00:25:00)" channel="Asianet News EPG Schedule &amp; Program Guide">
    <title>Nine @ 9-</title>
  </programme>
  <programme start="19-02-2024 04:10AM(00:25:00)" channel="Asianet News EPG Schedule &amp; Program Guide">
    <title>FIR Bulletin-</title>
  </programme>
  <programme start="19-02-2024 04:35AM(00:25:00)" channel="Asianet News EPG Schedule &amp; Program Guide">
    <title>Soorya Festival-</title>
  </programme>
  <programme start="19-02-2024 05:00AM(00:30:00)" channel="Asianet News EPG Schedule &amp; Program Guide">
    <title>News At 10-</title>
  </programme>
  <programme start="19-02-2024 05:30AM(00:25:00)" channel="Asianet News EPG Schedule &amp; Program Guide">
    <title>Kissan Krishideepam-</title>
  </programme>
  <programme start="19-02-2024 05:55AM(00:05:00)" channel="Asianet News EPG Schedule &amp; Program Guide">
    <title>Munshi-</title>
  </programme>
  <programme start="19-02-2024 06:00AM(00:25:00)" channel="Asianet News EPG Schedule &amp; Program Guide">
    <title>Asianet Varthakal-</title>
  </programme>
  <programme start="19-02-2024 06:25AM(00:05:00)" channel="Asianet News EPG Schedule &amp; Program Guide">
    <title>Body Guard-</title>
  </programme>
  <programme start="19-02-2024 06:30AM(00:30:00)" channel="Asianet News EPG Schedule &amp; Program Guide">
    <title>Asianet Varthakal-</title>
  </programme>
  <programme start="19-02-2024 07:00AM(00:30:00)" channel="Asianet News EPG Schedule &amp; Program Guide">
    <title>Namasthe Keralam-</title>
  </programme>
  <programme start="19-02-2024 07:30AM(00:30:00)" channel="Asianet News EPG Schedule &amp; Program Guide">
    <title>Namasthe Keralam-</title>
  </programme>
  <programme start="19-02-2024 08:00AM(00:15:00)" channel="Asianet News EPG Schedule &amp; Program Guide">
    <title>Innu Ethuvare-</title>
  </programme>
  <programme start="19-02-2024 08:15AM(00:15:00)" channel="Asianet News EPG Schedule &amp; Program Guide">
    <title>Sports News-</title>
  </programme>
  <programme start="19-02-2024 08:30AM(00:30:00)" channel="Asianet News EPG Schedule &amp; Program Guide">
    <title>Namasthe Keralam-</title>
  </programme>
  <programme start="19-02-2024 09:00AM(00:03:00)" channel="Asianet News EPG Schedule &amp; Program Guide">
    <title>Namasthe Keralam-</title>
  </programme>
  <programme start="19-02-2024 09:03AM(00:52:00)" channel="Asianet News EPG Schedule &amp; Program Guide">
    <title>Chuttuvattaom-</title>
  </programme>
  <programme start="19-02-2024 09:55AM(00:05:00)" channel="Asianet News EPG Schedule &amp; Program Guide">
    <title>Body Guard-</title>
  </programme>
  <programme start="19-02-2024 10:00AM(00:03:00)" channel="Asianet News EPG Schedule &amp; Program Guide">
    <title>Ippol Sambhavikkunnathu-</title>
  </programme>
  <programme start="19-02-2024 10:03AM(00:57:00)" channel="Asianet News EPG Schedule &amp; Program Guide">
    <title>Ippol Sambhavikkunnathu-</title>
  </programme>
  <programme start="19-02-2024 11:00AM(00:30:00)" channel="Asianet News EPG Schedule &amp; Program Guide">
    <title>Ippol Sambhavikkunnathu-</title>
  </programme>
  <programme start="19-02-2024 11:30AM(00:30:00)" channel="Asianet News EPG Schedule &amp; Program Guide">
    <title>Ippol Sambhavikkunnathu-</title>
  </programme>
  <programme start="19-02-2024 12:00PM(00:03:00)" channel="Asianet News EPG Schedule &amp; Program Guide">
    <title>Ippol Sambhavikkunnathu-</title>
  </programme>
  <programme start="19-02-2024 12:03PM(00:57:00)" channel="Asianet News EPG Schedule &amp; Program Guide">
    <title>Cover Story-</title>
  </programme>
  <programme start="19-02-2024 01:00PM(00:03:00)" channel="Asianet News EPG Schedule &amp; Program Guide">
    <title>News @ 1-</title>
  </programme>
  <programme start="19-02-2024 01:03PM(00:52:00)" channel="Asianet News EPG Schedule &amp; Program Guide">
    <title>Chuttuvattaom-</title>
  </programme>
  <programme start="19-02-2024 01:55PM(00:05:00)" channel="Asianet News EPG Schedule &amp; Program Guide">
    <title>Dr. Aster-</title>
  </programme>
  <programme start="19-02-2024 02:00PM(00:03:00)" channel="Asianet News EPG Schedule &amp; Program Guide">
    <title>News @ 14-</title>
  </programme>
  <programme start="19-02-2024 02:03PM(00:57:00)" channel="Asianet News EPG Schedule &amp; Program Guide">
    <title>Yuvajanolsavam 2024-</title>
  </programme>
  <programme start="19-02-2024 03:00PM(00:03:00)" channel="Asianet News EPG Schedule &amp; Program Guide">
    <title>Asianet Varthakal-</title>
  </programme>
  <programme start="19-02-2024 03:03PM(00:52:00)" channel="Asianet News EPG Schedule &amp; Program Guide">
    <title>Gulf Round Up-</title>
  </programme>
  <programme start="19-02-2024 03:55PM(00:05:00)" channel="Asianet News EPG Schedule &amp; Program Guide">
    <title>Body Guard-</title>
  </programme>
  <programme start="19-02-2024 04:00PM(00:03:00)" channel="Asianet News EPG Schedule &amp; Program Guide">
    <title>News At 4 PM-</title>
  </programme>
  <programme start="19-02-2024 04:03PM(00:57:00)" channel="Asianet News EPG Schedule &amp; Program Guide">
    <title>Gum-</title>
  </programme>
  <programme start="19-02-2024 05:00PM(00:03:00)" channel="Asianet News EPG Schedule &amp; Program Guide">
    <title>News-</title>
  </programme>
  <programme start="19-02-2024 05:03PM(00:52:00)" channel="Asianet News EPG Schedule &amp; Program Guide">
    <title>Yuvajanolsavam 2024-</title>
  </programme>
  <programme start="19-02-2024 05:55PM(00:05:00)" channel="Asianet News EPG Schedule &amp; Program Guide">
    <title>Munshi-</title>
  </programme>
  <programme start="19-02-2024 06:00PM(00:03:00)" channel="Asianet News EPG Schedule &amp; Program Guide">
    <title>News Time-</title>
  </programme>
  <programme start="19-02-2024 06:03PM(00:57:00)" channel="Asianet News EPG Schedule &amp; Program Guide">
    <title>Chuttuvattaom-</title>
  </programme>
  <programme start="19-02-2024 07:00PM(00:03:00)" channel="Asianet News EPG Schedule &amp; Program Guide">
    <title>Vartha Neram-</title>
  </programme>
  <programme start="19-02-2024 07:03PM(00:52:00)" channel="Asianet News EPG Schedule &amp; Program Guide">
    <title>Vartha Neram-</title>
  </programme>
  <programme start="19-02-2024 07:55PM(00:05:00)" channel="Asianet News EPG Schedule &amp; Program Guide">
    <title>Body Guard-</title>
  </programme>
  <programme start="19-02-2024 08:00PM(00:30:00)" channel="Asianet News EPG Schedule &amp; Program Guide">
    <title>News Hour Debate-</title>
  </programme>
  <programme start="19-02-2024 08:30PM(00:30:00)" channel="Asianet News EPG Schedule &amp; Program Guide">
    <title>News Hour Debate-</title>
  </programme>
  <programme start="19-02-2024 09:00PM(00:30:00)" channel="Asianet News EPG Schedule &amp; Program Guide">
    <title>Nine @ 9-</title>
  </programme>
  <programme start="19-02-2024 09:30PM(00:25:00)" channel="Asianet News EPG Schedule &amp; Program Guide">
    <title>News Reel-</title>
  </programme>
  <programme start="19-02-2024 09:55PM(00:05:00)" channel="Asianet News EPG Schedule &amp; Program Guide">
    <title>Munshi-</title>
  </programme>
  <programme start="19-02-2024 10:00PM(00:30:00)" channel="Asianet News EPG Schedule &amp; Program Guide">
    <title>News At 10-</title>
  </programme>
  <programme start="19-02-2024 10:30PM(00:25:00)" channel="Asianet News EPG Schedule &amp; Program Guide">
    <title>FIR Bulletin-</title>
  </programme>
  <programme start="19-02-2024 10:55PM(00:05:00)" channel="Asianet News EPG Schedule &amp; Program Guide">
    <title>Body Guard-</title>
  </programme>
  <programme start="19-02-2024 11:00PM(00:03:00)" channel="Asianet News EPG Schedule &amp; Program Guide">
    <title>Good Night News-</title>
  </programme>
  <programme start="19-02-2024 11:03PM(00:52:00)" channel="Asianet News EPG Schedule &amp; Program Guide">
    <title>Gulf News-</title>
  </programme>
  <programme start="19-02-2024 11:55PM(00:05:00)" channel="Asianet News EPG Schedule &amp; Program Guide">
    <title>Munshi-</title>
  </programme>
  <channel id="Asianet HD EPG Schedule &amp; Program Guide">
    <display-name>Asianet HD EPG Schedule &amp; Program Guide</display-name>
  </channel>
  <programme start="18-02-2024 01:30AM(02:00:00)" channel="Asianet HD EPG Schedule &amp; Program Guide">
    <title>Movie - Traffic- India 2011; Thriller &amp; Horror; Dir. Rajesh Pillai; Cast: Kunchako Boban, Sreenivasan. When a girl needs a heart transplant, a dying journalist's parents agree to help her.</title>
  </programme>
  <programme start="18-02-2024 03:30AM(02:30:00)" channel="Asianet HD EPG Schedule &amp; Program Guide">
    <title>Movie - Maari 2- India 2018; Action &amp; Crime; Dir. Balaji Mohan; Cast: Dhanush, Krishna Kulasekaran. Maari, a fun-loving gangster, faces a villain who has a grudge against him.</title>
  </programme>
  <programme start="18-02-2024 06:00AM(00:30:00)" channel="Asianet HD EPG Schedule &amp; Program Guide">
    <title>Best Of Comedy Stars- S03 E01. A compilation of some of the most hilarious skits by various comedians.</title>
  </programme>
  <programme start="18-02-2024 06:30AM(00:30:00)" channel="Asianet HD EPG Schedule &amp; Program Guide">
    <title>Best Of Comedy Stars- S03 E02. A compilation of some of the most hilarious skits by various comedians.</title>
  </programme>
  <programme start="18-02-2024 07:00AM(00:30:00)" channel="Asianet HD EPG Schedule &amp; Program Guide">
    <title>Soorya Festival 2023- E14. Renowned artists and musicians perform during the 2023 edition of the Soorya Festival.</title>
  </programme>
  <programme start="18-02-2024 07:30AM(00:30:00)" channel="Asianet HD EPG Schedule &amp; Program Guide">
    <title>Kissan Krishideepam- E1042. Experts talk about the developments in agriculture, animal husbandry and horticulture.</title>
  </programme>
  <programme start="18-02-2024 08:00AM(00:30:00)" channel="Asianet HD EPG Schedule &amp; Program Guide">
    <title>Best Of Comedy Stars- S03 E100. A compilation of some of the most hilarious skits by various comedians.</title>
  </programme>
  <programme start="18-02-2024 08:30AM(00:30:00)" channel="Asianet HD EPG Schedule &amp; Program Guide">
    <title>Best Of Comedy Stars- S03 E101. A compilation of some of the most hilarious skits by various comedians.</title>
  </programme>
  <programme start="18-02-2024 09:00AM(01:30:00)" channel="Asianet HD EPG Schedule &amp; Program Guide">
    <title>Star Singer- S09 E60. Talented singers perform different songs in a series of rounds and compete to win.</title>
  </programme>
  <programme start="18-02-2024 10:30AM(01:30:00)" channel="Asianet HD EPG Schedule &amp; Program Guide">
    <title>Star Singer- S09 E61. Talented singers perform different songs in a series of rounds and compete to win.</title>
  </programme>
  <programme start="18-02-2024 12:00PM(04:00:00)" channel="Asianet HD EPG Schedule &amp; Program Guide">
    <title>Movie - RRR- India 2022; Action &amp; Crime; Dir. S S Rajamouli; Cast: N T Rama Rao Jr, Ram Charan. Two friends on opposing sides of the British rule chart out a luminary path of freedom.</title>
  </programme>
  <programme start="18-02-2024 04:00PM(03:00:00)" channel="Asianet HD EPG Schedule &amp; Program Guide">
    <title>Malikappuram- E03. Lord Ayyappan enters the life of a young girl to help her overcome challenges.</title>
  </programme>
  <programme start="18-02-2024 07:00PM(00:30:00)" channel="Asianet HD EPG Schedule &amp; Program Guide">
    <title>Chempaneerpoovu- E21. A woman navigates through life when she meets a man, taking her life on a new course.</title>
  </programme>
  <programme start="18-02-2024 07:30PM(03:00:00)" channel="Asianet HD EPG Schedule &amp; Program Guide">
    <title>Movie - Garudan (Premiere)- India 2023; Action &amp; Crime; Dir. Arun Varma; Cast: Suresh Gopi, Biju Menon. A policeman and a professor clash over a rape case that reveals their hidden secrets.</title>
  </programme>
  <programme start="18-02-2024 10:30PM(02:30:00)" channel="Asianet HD EPG Schedule &amp; Program Guide">
    <title>Movie - Sulaikha Manzil- India 2023; Romance; Dir. Ashraf Hamza; Cast: Lukman Avaran, Anarkali Marikar. Chaos ensues as Ameen tries to get closer to Haala before their last-minute wedding.</title>
  </programme>
  <programme start="19-02-2024 01:00AM(02:30:00)" channel="Asianet HD EPG Schedule &amp; Program Guide">
    <title>Movie - Mampazhakkalam- India 2004; Drama; Dir. Joshi; Cast: Mohanlal, Shobana. Chandran has a chance meeting with his childhood lover and hopes to reconnect with her.</title>
  </programme>
  <programme start="19-02-2024 03:30AM(02:30:00)" channel="Asianet HD EPG Schedule &amp; Program Guide">
    <title>Movie - Veruthe Oru Bharya- India 2008; Drama; Dir. Aku Akbar; Cast: Jayaram, Gopika. Due to an unexpected turn of events, Sagunan realises the value of women.</title>
  </programme>
  <programme start="19-02-2024 06:00AM(03:00:00)" channel="Asianet HD EPG Schedule &amp; Program Guide">
    <title>TBA- TBA</title>
  </programme>
  <programme start="19-02-2024 09:00AM(03:00:00)" channel="Asianet HD EPG Schedule &amp; Program Guide">
    <title>TBA- TBA</title>
  </programme>
  <programme start="19-02-2024 12:00PM(03:00:00)" channel="Asianet HD EPG Schedule &amp; Program Guide">
    <title>TBA- TBA</title>
  </programme>
  <programme start="19-02-2024 03:00PM(03:00:00)" channel="Asianet HD EPG Schedule &amp; Program Guide">
    <title>TBA- TBA</title>
  </programme>
  <programme start="19-02-2024 06:00PM(03:00:00)" channel="Asianet HD EPG Schedule &amp; Program Guide">
    <title>TBA- TBA</title>
  </programme>
  <programme start="19-02-2024 09:00PM(03:00:00)" channel="Asianet HD EPG Schedule &amp; Program Guide">
    <title>TBA- TBA</title>
  </programme>
  <programme start="20-02-2024 12:00AM(02:30:00)" channel="Asianet HD EPG Schedule &amp; Program Guide">
    <title>Movie - Photographer- India 2006; Drama; Dir. Ranjan Pramod; Cast: Mohanlal, Neethasree. A photographer puts himself in trouble when he decides to fight against a notorious cop.</title>
  </programme>
  <channel id="Asianet Movies HD EPG Schedule &amp; Program Guide">
    <display-name>Asianet Movies HD EPG Schedule &amp; Program Guide</display-name>
  </channel>
  <programme start="18-02-2024 12:40AM(02:50:00)" channel="Asianet Movies HD EPG Schedule &amp; Program Guide">
    <title>Alexander The Great- India 2010; Action &amp; Crime; Dir. Murali Nagavally; Cast: Mohanlal, Bala. Prathapa Verma leaves all his wealth for his illegitimate son which angers his family.</title>
  </programme>
  <programme start="18-02-2024 03:30AM(02:30:00)" channel="Asianet Movies HD EPG Schedule &amp; Program Guide">
    <title>Koottu- India 2004; Drama; Dir. Jayaprakash; Cast: Richard Rishi, Aravind Akash. Friends Hari and Balu's life takes a turn when Balu disappears and Hari tries to find him.</title>
  </programme>
  <programme start="18-02-2024 06:00AM(00:30:00)" channel="Asianet Movies HD EPG Schedule &amp; Program Guide">
    <title>Play Back- An extensive compilation of enjoyable fast-paced songs from Malayalam movies.</title>
  </programme>
  <programme start="18-02-2024 06:30AM(00:30:00)" channel="Asianet Movies HD EPG Schedule &amp; Program Guide">
    <title>Play Back- An extensive compilation of enjoyable fast-paced songs from Malayalam movies.</title>
  </programme>
  <programme start="18-02-2024 07:00AM(03:00:00)" channel="Asianet Movies HD EPG Schedule &amp; Program Guide">
    <title>Sunday Holiday- India 2017; Comedy; Dir. Jis Joy; Cast: Asif Ali, Aparna Balamurali. Unni meets a director to narrate his story about a man who plans to start life afresh.</title>
  </programme>
  <programme start="18-02-2024 10:00AM(03:00:00)" channel="Asianet Movies HD EPG Schedule &amp; Program Guide">
    <title>Jaya Jaya Jaya Jaya Hey- India 2022; Comedy; Dir. Vipin Das; Cast: Darshana Rajendran, Basil Joseph. Chaos ensues when a woman decides to retaliate against her violent husband.</title>
  </programme>
  <programme start="18-02-2024 01:00PM(03:00:00)" channel="Asianet Movies HD EPG Schedule &amp; Program Guide">
    <title>Chitta- India 2023; Thriller &amp; Horror; Dir. S U Arun Kumar; Cast: Siddharth, Nimisha Sajayan. After his niece goes missing, a man goes against all odds to find her.</title>
  </programme>
  <programme start="18-02-2024 04:00PM(03:00:00)" channel="Asianet Movies HD EPG Schedule &amp; Program Guide">
    <title>Lucifer- India 2019; Action &amp; Crime; Dir. Prithviraj Sukumaran; Cast: Mohanlal, Vivek Oberoi. A mysterious man joins a power struggle surrounding a political party and its leadership.</title>
  </programme>
  <programme start="18-02-2024 07:00PM(02:30:00)" channel="Asianet Movies HD EPG Schedule &amp; Program Guide">
    <title>Valatty- India 2023; Adventure; Dir. Devan; Cast: Roshan Mathews, Raveena Ravi. Complications arise when two dogs run away from their homes and one of them gets abducted.</title>
  </programme>
  <programme start="18-02-2024 09:30PM(03:00:00)" channel="Asianet Movies HD EPG Schedule &amp; Program Guide">
    <title>Iratta- India 2023; Thriller &amp; Horror; Dir. Rohit M G Krishnan; Cast: Joju George, Anjali. When a police inspector is found dead, his twin brother must unearth the truth.</title>
  </programme>
  <programme start="19-02-2024 12:40AM(03:00:00)" channel="Asianet Movies HD EPG Schedule &amp; Program Guide">
    <title>Movie- Drama. Movie</title>
  </programme>
  <programme start="19-02-2024 03:40AM(02:20:00)" channel="Asianet Movies HD EPG Schedule &amp; Program Guide">
    <title>Movie- Drama. Movie</title>
  </programme>
  <programme start="19-02-2024 06:00AM(00:30:00)" channel="Asianet Movies HD EPG Schedule &amp; Program Guide">
    <title>Play Back- An extensive compilation of enjoyable fast-paced songs from Malayalam movies.</title>
  </programme>
  <programme start="19-02-2024 06:30AM(00:30:00)" channel="Asianet Movies HD EPG Schedule &amp; Program Guide">
    <title>Play Back- An extensive compilation of enjoyable fast-paced songs from Malayalam movies.</title>
  </programme>
  <programme start="19-02-2024 07:00AM(03:00:00)" channel="Asianet Movies HD EPG Schedule &amp; Program Guide">
    <title>Movie- Drama. Movie</title>
  </programme>
  <programme start="19-02-2024 10:00AM(03:00:00)" channel="Asianet Movies HD EPG Schedule &amp; Program Guide">
    <title>Movie- Drama. Movie</title>
  </programme>
  <programme start="19-02-2024 01:00PM(03:00:00)" channel="Asianet Movies HD EPG Schedule &amp; Program Guide">
    <title>Movie- Drama. Movie</title>
  </programme>
  <programme start="19-02-2024 04:00PM(03:00:00)" channel="Asianet Movies HD EPG Schedule &amp; Program Guide">
    <title>Movie- Drama. Movie</title>
  </programme>
  <programme start="19-02-2024 07:00PM(03:05:00)" channel="Asianet Movies HD EPG Schedule &amp; Program Guide">
    <title>Movie- Drama. Movie</title>
  </programme>
  <programme start="19-02-2024 10:05PM(02:50:00)" channel="Asianet Movies HD EPG Schedule &amp; Program Guide">
    <title>Movie- Drama. Movie</title>
  </programme>
  <programme start="20-02-2024 12:55AM(02:35:00)" channel="Asianet Movies HD EPG Schedule &amp; Program Guide">
    <title>Movie- Drama. Movie</title>
  </programme>
  <channel id="Asianet Plus EPG Schedule &amp; Program Guide">
    <display-name>Asianet Plus EPG Schedule &amp; Program Guide</display-name>
  </channel>
  <programme start="18-02-2024 02:00AM(01:00:00)" channel="Asianet Plus EPG Schedule &amp; Program Guide">
    <title>Comedy Stars- S02 E646. Talented comedians stage performances to impress the judges and win the title.</title>
  </programme>
  <programme start="18-02-2024 03:00AM(02:30:00)" channel="Asianet Plus EPG Schedule &amp; Program Guide">
    <title>Movie - Janmantharam- India 1988; Drama; Dir. Thampi Kannanthanam; Cast: Balachandra Menon, Shobhana. Four bachelors land in trouble after opposing an evil landlord, Panikkar.</title>
  </programme>
  <programme start="18-02-2024 05:30AM(02:30:00)" channel="Asianet Plus EPG Schedule &amp; Program Guide">
    <title>Movie - Kadha Thudarunnu- India 2010; Drama; Dir. Sathyan Anthikad; Cast: Mamtha Mohandas, Jayaram. A widower's life takes a turn when Preman, an auto-rickshaw driver, enters her life.</title>
  </programme>
  <programme start="18-02-2024 08:00AM(00:30:00)" channel="Asianet Plus EPG Schedule &amp; Program Guide">
    <title>Devi Mahathmyam- E87. An anthology of stories which deal with the various forms and legends of Goddess Durga.</title>
  </programme>
  <programme start="18-02-2024 08:30AM(00:25:00)" channel="Asianet Plus EPG Schedule &amp; Program Guide">
    <title>Kailasanadhan- E316. Shani reports to Parvati that Shiva played the 'damaruk' on his request.</title>
  </programme>
  <programme start="18-02-2024 08:55AM(00:05:00)" channel="Asianet Plus EPG Schedule &amp; Program Guide">
    <title>Paribhavam Parvathi- E1073. A young couple and their daughter deal with day-to-day problems in a comical way.</title>
  </programme>
  <programme start="18-02-2024 09:00AM(03:00:00)" channel="Asianet Plus EPG Schedule &amp; Program Guide">
    <title>Movie - Arabikkatha- India 2007; Drama; Dir. Lal Jose; Cast: Sreenivasan, Indrajith. Mukundan, a hardcore communist, is shunned in society for his outdated views.</title>
  </programme>
  <programme start="18-02-2024 12:00PM(00:30:00)" channel="Asianet Plus EPG Schedule &amp; Program Guide">
    <title>Soorya Festival 2023- E14. Renowned artists and musicians perform during the 2023 edition of the Soorya Festival.</title>
  </programme>
  <programme start="18-02-2024 12:30PM(02:30:00)" channel="Asianet Plus EPG Schedule &amp; Program Guide">
    <title>Movie - Jamna Pyari- India 2015; Comedy; Dir. Thomas Sebastian; Cast: Kunchacko Boban, Gayathri Suresh. Parvathy seeks Vasoottan's help to deliver a hundred Jamnapari goats to save her farm.</title>
  </programme>
  <programme start="18-02-2024 03:00PM(03:00:00)" channel="Asianet Plus EPG Schedule &amp; Program Guide">
    <title>Movie - Pokkiri Raja- India 2010; Drama; Dir. Vysakh; Cast: Mammootty, Prithviraj. Raja's father, who deserts him, seeks his help when his younger son lands in prison.</title>
  </programme>
  <programme start="18-02-2024 06:00PM(00:30:00)" channel="Asianet Plus EPG Schedule &amp; Program Guide">
    <title>Devi Mahathmyam- E88. An anthology of stories which deal with the various forms and legends of Goddess Durga.</title>
  </programme>
  <programme start="18-02-2024 06:30PM(00:30:00)" channel="Asianet Plus EPG Schedule &amp; Program Guide">
    <title>Kailasanadhan- E317. Sumali's soldiers set fire on the ashram. Enraged Parvati becomes Kali. Repeat - Mon,Tue,Wed,Thu,Fri,Sun 8:30 am</title>
  </programme>
  <programme start="18-02-2024 07:00PM(01:00:00)" channel="Asianet Plus EPG Schedule &amp; Program Guide">
    <title>Comedy Stars- S02 E647. Talented comedians stage performances to impress the judges and win the title. Repeat - Mon - Fri 12:30 pm</title>
  </programme>
  <programme start="18-02-2024 08:00PM(03:30:00)" channel="Asianet Plus EPG Schedule &amp; Program Guide">
    <title>Comedy Stars- S02 E01. Four teams of comedians compete against each other to win the coveted title.</title>
  </programme>
  <programme start="18-02-2024 11:30PM(02:30:00)" channel="Asianet Plus EPG Schedule &amp; Program Guide">
    <title>Movie - Vazhunnoor- India 1999; Action &amp; Crime; Dir. Joshiy; Cast: Suresh Gopi, Samyuktha Varma. The rivalry between two families causes complications in the lives of their children.</title>
  </programme>
  <programme start="19-02-2024 02:00AM(01:00:00)" channel="Asianet Plus EPG Schedule &amp; Program Guide">
    <title>Badai Bungalow- S01 E39. The host interviews and entertain celebrities from the Malayalam film industry. Repeat - Tue - Sat 2:00 am</title>
  </programme>
  <programme start="19-02-2024 03:00AM(02:30:00)" channel="Asianet Plus EPG Schedule &amp; Program Guide">
    <title>Movie - Swarnam- India 2008; Drama; Dir. Venugopan; Cast: Kalabhavan Mani, Praveena. Divakaran is a selfish, stingy man who dislikes his wife Radha and her orphaned niece.</title>
  </programme>
  <programme start="19-02-2024 05:30AM(02:30:00)" channel="Asianet Plus EPG Schedule &amp; Program Guide">
    <title>Movie - Zachariayude Garbhinikal- India 2013; Drama; Dir. Aneesh Anwar; Cast: Lal, Sanusha. Zaria, an eighteen-year-old girl, gives birth to a baby and hands it over to a doctor.</title>
  </programme>
  <programme start="19-02-2024 08:00AM(00:30:00)" channel="Asianet Plus EPG Schedule &amp; Program Guide">
    <title>Devi Mahathmyam- E06. An anthology of stories which deal with the various forms and legends of Goddess Durga.</title>
  </programme>
  <programme start="19-02-2024 08:30AM(00:30:00)" channel="Asianet Plus EPG Schedule &amp; Program Guide">
    <title>Kailasanadhan- E218. Parvathy becomes very upset of having eventually landed her foot on Shiva's chest.</title>
  </programme>
  <programme start="19-02-2024 09:00AM(00:30:00)" channel="Asianet Plus EPG Schedule &amp; Program Guide">
    <title>Best Of Comedy Stars- S02 E18. A compilation of some of the most hilarious skits by various comedians.</title>
  </programme>
  <programme start="19-02-2024 09:30AM(03:00:00)" channel="Asianet Plus EPG Schedule &amp; Program Guide">
    <title>Movie - Senior Mandrake- India 2010; Comedy; Dir. Ali Akbar; Cast: Jagathi Sreekumar, Jagadish Kumar. Two friends get into trouble when their ill-fated statue returns to their house.</title>
  </programme>
  <programme start="19-02-2024 12:30PM(01:00:00)" channel="Asianet Plus EPG Schedule &amp; Program Guide">
    <title>Comedy Stars- S02 E548. Talented comedians stage performances to impress the judges and win the title.</title>
  </programme>
  <programme start="19-02-2024 01:30PM(01:00:00)" channel="Asianet Plus EPG Schedule &amp; Program Guide">
    <title>Badai Bungalow- S01 E82. The host interacts with and entertains celebrities Chiitra Shenoy and Sonu.</title>
  </programme>
  <programme start="19-02-2024 02:30PM(00:30:00)" channel="Asianet Plus EPG Schedule &amp; Program Guide">
    <title>Best Of Comedy Stars- S02 E18. A compilation of some of the most hilarious skits by various comedians.</title>
  </programme>
  <programme start="19-02-2024 03:00PM(03:00:00)" channel="Asianet Plus EPG Schedule &amp; Program Guide">
    <title>Movie - Aye Auto- India 1990; Romance; Dir. Venu Nagavalli; Cast: Mohanlal, Rekha. A young girl falls in love with a rickshaw driver but faces opposition from her family.</title>
  </programme>
  <programme start="19-02-2024 06:00PM(00:30:00)" channel="Asianet Plus EPG Schedule &amp; Program Guide">
    <title>Devi Mahathmyam- E16. An anthology of stories which deal with the various forms and legends of Goddess Durga.</title>
  </programme>
  <programme start="19-02-2024 06:30PM(00:30:00)" channel="Asianet Plus EPG Schedule &amp; Program Guide">
    <title>Kailasanadhan- E22. Parvathy slips into a deep slumber after Shiva begins the 'Tantrika Mantra'. Repeat - Mon,Tue,Wed,Thu,Fri,Sun 8:30 am</title>
  </programme>
  <programme start="19-02-2024 07:00PM(01:00:00)" channel="Asianet Plus EPG Schedule &amp; Program Guide">
    <title>Comedy Stars- S02 E549. Talented comedians stage performances to impress the judges and win the title.</title>
  </programme>
  <programme start="19-02-2024 08:00PM(01:00:00)" channel="Asianet Plus EPG Schedule &amp; Program Guide">
    <title>Star Singer Junior- S03 E18. Children under the age of eighteen participate in a singing competition.</title>
  </programme>
  <programme start="19-02-2024 09:00PM(01:00:00)" channel="Asianet Plus EPG Schedule &amp; Program Guide">
    <title>Badai Bungalow- S01 E39. The host interviews and entertain celebrities from the Malayalam film industry. Repeat - Tue - Sat 2:00 am</title>
  </programme>
  <programme start="19-02-2024 10:00PM(01:00:00)" channel="Asianet Plus EPG Schedule &amp; Program Guide">
    <title>Comedy Stars- S02 E549. Talented comedians stage performances to impress the judges and win the title.</title>
  </programme>
  <programme start="19-02-2024 11:00PM(03:00:00)" channel="Asianet Plus EPG Schedule &amp; Program Guide">
    <title>Movie - Metro City- India 2020; Thriller &amp; Horror; Dir. Lokesh Kanagaraj; Cast: Sundeep Kishan, Sri. The lives of four youngsters intertwine in the big city as they face horrors.</title>
  </programme>
  <channel id="DD Malayalam EPG Schedule &amp; Program Guide">
    <display-name>DD Malayalam EPG Schedule &amp; Program Guide</display-name>
  </channel>
  <programme start="18-02-2024 12:00AM(01:00:00)" channel="DD Malayalam EPG Schedule &amp; Program Guide">
    <title>Movie - Makal- Movie - Makal</title>
  </programme>
  <programme start="18-02-2024 01:00AM(00:30:00)" channel="DD Malayalam EPG Schedule &amp; Program Guide">
    <title>Ullekham Kavithayile Velichangal- Talented singers are invited to lend their voices and musically express Ullekham poetry.</title>
  </programme>
  <programme start="18-02-2024 01:30AM(00:30:00)" channel="DD Malayalam EPG Schedule &amp; Program Guide">
    <title>Madhuram 18- The presenter shares current affairs and discusses their resulting impacts.</title>
  </programme>
  <programme start="18-02-2024 02:00AM(00:30:00)" channel="DD Malayalam EPG Schedule &amp; Program Guide">
    <title>SIET- SIET introduces its activities and educational software for programming.</title>
  </programme>
  <programme start="18-02-2024 02:30AM(00:30:00)" channel="DD Malayalam EPG Schedule &amp; Program Guide">
    <title>Amrithabharatham- The host presents the latest updates and top news stories from across India.</title>
  </programme>
  <programme start="18-02-2024 03:00AM(00:30:00)" channel="DD Malayalam EPG Schedule &amp; Program Guide">
    <title>Kathakali- Take a look at the Kathakali dance performance by Kottakal Chandrashekhar.</title>
  </programme>
  <programme start="18-02-2024 03:30AM(01:00:00)" channel="DD Malayalam EPG Schedule &amp; Program Guide">
    <title>Doctor's Speak- Medical experts discuss various questions asked by people about COVID-19.</title>
  </programme>
  <programme start="18-02-2024 04:30AM(00:30:00)" channel="DD Malayalam EPG Schedule &amp; Program Guide">
    <title>Swathanthrathinte Amrit Maholsav- The notable works of both popular and lesser-known freedom fighters are presented.</title>
  </programme>
  <programme start="18-02-2024 05:00AM(01:00:00)" channel="DD Malayalam EPG Schedule &amp; Program Guide">
    <title>Chembai Music Festival- Highlights of the a music festival held in honour of Chembai Vaidyanatha Bhagavathar.</title>
  </programme>
  <programme start="18-02-2024 06:00AM(00:30:00)" channel="DD Malayalam EPG Schedule &amp; Program Guide">
    <title>Devotional Songs- A comprehensive compilation of various devotional songs performed by different artists.</title>
  </programme>
  <programme start="18-02-2024 06:30AM(00:30:00)" channel="DD Malayalam EPG Schedule &amp; Program Guide">
    <title>Enswaram- Popular playback singers pay tribute to their teachers by singing their favourite songs.</title>
  </programme>
  <programme start="18-02-2024 07:00AM(00:30:00)" channel="DD Malayalam EPG Schedule &amp; Program Guide">
    <title>SIET- SIET introduces its activities and educational software for programming.</title>
  </programme>
  <programme start="18-02-2024 07:30AM(00:30:00)" channel="DD Malayalam EPG Schedule &amp; Program Guide">
    <title>Varthakal- The host presents some of the latest news stories, current affairs and developments.</title>
  </programme>
  <programme start="18-02-2024 08:00AM(00:30:00)" channel="DD Malayalam EPG Schedule &amp; Program Guide">
    <title>Swathanthrathinte Amrit Maholsav- The notable works of both popular and lesser-known freedom fighters are presented.</title>
  </programme>
  <programme start="18-02-2024 08:30AM(00:30:00)" channel="DD Malayalam EPG Schedule &amp; Program Guide">
    <title>Ullekham Kavithayile Velichangal- Talented singers are invited to lend their voices and musically express Ullekham poetry.</title>
  </programme>
  <programme start="18-02-2024 09:00AM(00:30:00)" channel="DD Malayalam EPG Schedule &amp; Program Guide">
    <title>Priya Keralam- The host goes on an expedition to Kerala to know more about the culture and traditions.</title>
  </programme>
  <programme start="18-02-2024 09:30AM(00:30:00)" channel="DD Malayalam EPG Schedule &amp; Program Guide">
    <title>Noorumeni- An agricultural expert talks about different types of farms and farming techniques.</title>
  </programme>
  <programme start="18-02-2024 10:00AM(00:10:00)" channel="DD Malayalam EPG Schedule &amp; Program Guide">
    <title>Varthakal- The host presents some of the latest news stories, current affairs and developments.</title>
  </programme>
  <programme start="18-02-2024 10:10AM(00:25:00)" channel="DD Malayalam EPG Schedule &amp; Program Guide">
    <title>Madhyama Jalakam- The host updates on the leading periodicals and critically analyses their contents.</title>
  </programme>
  <programme start="18-02-2024 10:35AM(00:25:00)" channel="DD Malayalam EPG Schedule &amp; Program Guide">
    <title>Amrithabharatham- The host presents the latest updates and top news stories from across India.</title>
  </programme>
  <programme start="18-02-2024 11:00AM(00:10:00)" channel="DD Malayalam EPG Schedule &amp; Program Guide">
    <title>Varthakal- The host presents some of the latest news stories, current affairs and developments.</title>
  </programme>
  <programme start="18-02-2024 11:10AM(00:20:00)" channel="DD Malayalam EPG Schedule &amp; Program Guide">
    <title>KTB Bharat Hain Hum- Lakshmi Bai Part 2: The journey of some of the unrecognised freedom fighters of India.</title>
  </programme>
  <programme start="18-02-2024 11:30AM(00:30:00)" channel="DD Malayalam EPG Schedule &amp; Program Guide">
    <title>Madhuram 18- The presenter shares current affairs and discusses their resulting impacts.</title>
  </programme>
  <programme start="18-02-2024 12:00PM(00:10:00)" channel="DD Malayalam EPG Schedule &amp; Program Guide">
    <title>Varthakal- The host presents some of the latest news stories, current affairs and developments.</title>
  </programme>
  <programme start="18-02-2024 12:10PM(00:50:00)" channel="DD Malayalam EPG Schedule &amp; Program Guide">
    <title>Koottinoru Pattu- The host talks to singers who sing their best songs and answer questions from the viewers.</title>
  </programme>
  <programme start="18-02-2024 01:00PM(00:30:00)" channel="DD Malayalam EPG Schedule &amp; Program Guide">
    <title>Varthakal- The host presents some of the latest news stories, current affairs and developments.</title>
  </programme>
  <programme start="18-02-2024 01:30PM(00:30:00)" channel="DD Malayalam EPG Schedule &amp; Program Guide">
    <title>Cookery- Homemakers and chefs share easy recipes to make some of the most interesting dishes.</title>
  </programme>
  <programme start="18-02-2024 02:00PM(00:30:00)" channel="DD Malayalam EPG Schedule &amp; Program Guide">
    <title>Interview With Anandapadmanabhavan- Part 1</title>
  </programme>
  <programme start="18-02-2024 02:30PM(00:30:00)" channel="DD Malayalam EPG Schedule &amp; Program Guide">
    <title>Employment News &amp; Career Guidance- The host sheds light on employment opportunities and counsellors offer career advice.</title>
  </programme>
  <programme start="18-02-2024 03:00PM(00:10:00)" channel="DD Malayalam EPG Schedule &amp; Program Guide">
    <title>Varthakal- The host presents some of the latest news stories, current affairs and developments.</title>
  </programme>
  <programme start="18-02-2024 03:10PM(00:50:00)" channel="DD Malayalam EPG Schedule &amp; Program Guide">
    <title>Om Namah Shivaya- Mega: The Hindu saga of Lord Shiva - Bolenath - Shankar and his consort Shakti/Parvati.</title>
  </programme>
  <programme start="18-02-2024 04:00PM(00:10:00)" channel="DD Malayalam EPG Schedule &amp; Program Guide">
    <title>Varthakal- The host presents some of the latest news stories, current affairs and developments.</title>
  </programme>
  <programme start="18-02-2024 04:10PM(00:50:00)" channel="DD Malayalam EPG Schedule &amp; Program Guide">
    <title>Om Namah Shivaya- Mega: The Hindu saga of Lord Shiva - Bolenath - Shankar and his consort Shakti/Parvati.</title>
  </programme>
  <programme start="18-02-2024 05:00PM(00:10:00)" channel="DD Malayalam EPG Schedule &amp; Program Guide">
    <title>News Headlines- The presenter reports political and socio-economic news from India and around the world.</title>
  </programme>
  <programme start="18-02-2024 05:10PM(00:25:00)" channel="DD Malayalam EPG Schedule &amp; Program Guide">
    <title>Arogyaveedhi- Dr. P.v. Pradeep Part 2: The host invites a medical expert and discusses matters of health and medicines in detail.</title>
  </programme>
  <programme start="18-02-2024 05:35PM(00:25:00)" channel="DD Malayalam EPG Schedule &amp; Program Guide">
    <title>SIET- SIET introduces its activities and educational software for programming.</title>
  </programme>
  <programme start="18-02-2024 06:00PM(00:10:00)" channel="DD Malayalam EPG Schedule &amp; Program Guide">
    <title>Varthakal- The host presents some of the latest news stories, current affairs and developments.</title>
  </programme>
  <programme start="18-02-2024 06:10PM(00:25:00)" channel="DD Malayalam EPG Schedule &amp; Program Guide">
    <title>Krishidarshan- An expert gives advice on farming techniques and how to reap a good harvest.</title>
  </programme>
  <programme start="18-02-2024 06:35PM(00:25:00)" channel="DD Malayalam EPG Schedule &amp; Program Guide">
    <title>World This Week- The host presents the latest news pertaining to various events from around the world.</title>
  </programme>
  <programme start="18-02-2024 07:00PM(00:30:00)" channel="DD Malayalam EPG Schedule &amp; Program Guide">
    <title>Varthakal- The host presents some of the latest news stories, current affairs and developments.</title>
  </programme>
  <programme start="18-02-2024 07:30PM(00:30:00)" channel="DD Malayalam EPG Schedule &amp; Program Guide">
    <title>Enswaram- Popular playback singers pay tribute to their teachers by singing their favourite songs.</title>
  </programme>
  <programme start="18-02-2024 08:00PM(01:00:00)" channel="DD Malayalam EPG Schedule &amp; Program Guide">
    <title>Koottinoru Pattu- The host talks to singers who sing their best songs and answer questions from the viewers.</title>
  </programme>
  <programme start="18-02-2024 09:00PM(01:00:00)" channel="DD Malayalam EPG Schedule &amp; Program Guide">
    <title>Kilivathil- Talented artists perform a compilation of songs composed by renowned singers.</title>
  </programme>
  <programme start="18-02-2024 10:00PM(00:30:00)" channel="DD Malayalam EPG Schedule &amp; Program Guide">
    <title>Madhyama Jalakam- The host updates on the leading periodicals and critically analyses their contents.</title>
  </programme>
  <programme start="18-02-2024 10:30PM(00:30:00)" channel="DD Malayalam EPG Schedule &amp; Program Guide">
    <title>World This Week- The host presents the latest news pertaining to various events from around the world.</title>
  </programme>
  <programme start="18-02-2024 11:00PM(00:30:00)" channel="DD Malayalam EPG Schedule &amp; Program Guide">
    <title>Employment News &amp; Career Guidance- The host sheds light on employment opportunities and counsellors offer career advice.</title>
  </programme>
  <programme start="18-02-2024 11:30PM(00:30:00)" channel="DD Malayalam EPG Schedule &amp; Program Guide">
    <title>Interview With Anandapadmanabhavan- Part 1</title>
  </programme>
  <programme start="19-02-2024 12:00AM(01:00:00)" channel="DD Malayalam EPG Schedule &amp; Program Guide">
    <title>Koottinoru Pattu- The host talks to singers who sing their best songs and answer questions from the viewers.</title>
  </programme>
  <programme start="19-02-2024 01:00AM(01:00:00)" channel="DD Malayalam EPG Schedule &amp; Program Guide">
    <title>Chembai Music Festival 2022- Artists perform in an annual music festival held in memory of Chembai Bhagavatar in 2022.</title>
  </programme>
  <programme start="19-02-2024 02:00AM(00:30:00)" channel="DD Malayalam EPG Schedule &amp; Program Guide">
    <title>SIET- SIET introduces its activities and educational software for programming.</title>
  </programme>
  <programme start="19-02-2024 02:30AM(00:30:00)" channel="DD Malayalam EPG Schedule &amp; Program Guide">
    <title>Cookery- Homemakers and chefs share easy recipes to make some of the most interesting dishes.</title>
  </programme>
  <programme start="19-02-2024 03:00AM(01:00:00)" channel="DD Malayalam EPG Schedule &amp; Program Guide">
    <title>Kilivathil- Talented artists perform a compilation of songs composed by renowned singers.</title>
  </programme>
  <programme start="19-02-2024 04:00AM(00:30:00)" channel="DD Malayalam EPG Schedule &amp; Program Guide">
    <title>Interview With Anandapadmanabhavan- Part 1</title>
  </programme>
  <programme start="19-02-2024 04:30AM(00:30:00)" channel="DD Malayalam EPG Schedule &amp; Program Guide">
    <title>Krishidarshan- An expert gives advice on farming techniques and how to reap a good harvest.</title>
  </programme>
  <programme start="19-02-2024 05:00AM(01:00:00)" channel="DD Malayalam EPG Schedule &amp; Program Guide">
    <title>Chembai Music Festival- Highlights of the a music festival held in honour of Chembai Vaidyanatha Bhagavathar.</title>
  </programme>
  <programme start="19-02-2024 06:00AM(00:30:00)" channel="DD Malayalam EPG Schedule &amp; Program Guide">
    <title>Devotional Songs- A comprehensive compilation of various devotional songs performed by different artists.</title>
  </programme>
  <programme start="19-02-2024 06:30AM(00:15:00)" channel="DD Malayalam EPG Schedule &amp; Program Guide">
    <title>Sanskrit News- Updates on the latest news, current affairs, events and happenings presented in Sanskrit.</title>
  </programme>
  <programme start="19-02-2024 06:45AM(00:15:00)" channel="DD Malayalam EPG Schedule &amp; Program Guide">
    <title>Employment News- The host presents the latest employment opportunities and vacancies in government offices.</title>
  </programme>
  <programme start="19-02-2024 07:00AM(00:30:00)" channel="DD Malayalam EPG Schedule &amp; Program Guide">
    <title>SIET- SIET introduces its activities and educational software for programming.</title>
  </programme>
  <programme start="19-02-2024 07:30AM(00:30:00)" channel="DD Malayalam EPG Schedule &amp; Program Guide">
    <title>Varthakal- The host presents some of the latest news stories, current affairs and developments.</title>
  </programme>
  <programme start="19-02-2024 08:00AM(00:30:00)" channel="DD Malayalam EPG Schedule &amp; Program Guide">
    <title>World This Week- The host presents the latest news pertaining to various events from around the world.</title>
  </programme>
  <programme start="19-02-2024 08:30AM(00:30:00)" channel="DD Malayalam EPG Schedule &amp; Program Guide">
    <title>Kathakali Duryodhanavadham- Part 3: Kathakali dancers depict the slaying of Duryodhana in the Mahabharata.</title>
  </programme>
  <programme start="19-02-2024 09:00AM(01:00:00)" channel="DD Malayalam EPG Schedule &amp; Program Guide">
    <title>Kilivathil- Talented artists perform a compilation of songs composed by renowned singers.</title>
  </programme>
  <programme start="19-02-2024 10:00AM(00:10:00)" channel="DD Malayalam EPG Schedule &amp; Program Guide">
    <title>Varthakal- The host presents some of the latest news stories, current affairs and developments.</title>
  </programme>
  <programme start="19-02-2024 10:10AM(00:50:00)" channel="DD Malayalam EPG Schedule &amp; Program Guide">
    <title>Doctor's Speak- Medical experts discuss various questions asked by people about COVID-19.</title>
  </programme>
  <programme start="19-02-2024 11:00AM(00:10:00)" channel="DD Malayalam EPG Schedule &amp; Program Guide">
    <title>Varthakal- The host presents some of the latest news stories, current affairs and developments.</title>
  </programme>
  <programme start="19-02-2024 11:10AM(00:25:00)" channel="DD Malayalam EPG Schedule &amp; Program Guide">
    <title>Interview With Anandapadmanabhavan- Part 1</title>
  </programme>
  <programme start="19-02-2024 11:35AM(00:25:00)" channel="DD Malayalam EPG Schedule &amp; Program Guide">
    <title>Krishidarshan- An expert gives advice on farming techniques and how to reap a good harvest.</title>
  </programme>
  <programme start="19-02-2024 12:00PM(00:10:00)" channel="DD Malayalam EPG Schedule &amp; Program Guide">
    <title>Varthakal- The host presents some of the latest news stories, current affairs and developments.</title>
  </programme>
  <programme start="19-02-2024 12:10PM(00:25:00)" channel="DD Malayalam EPG Schedule &amp; Program Guide">
    <title>Swathanthrathinte Amrit Maholsav- The notable works of both popular and lesser-known freedom fighters are presented.</title>
  </programme>
  <programme start="19-02-2024 12:35PM(00:25:00)" channel="DD Malayalam EPG Schedule &amp; Program Guide">
    <title>Enswaram- Popular playback singers pay tribute to their teachers by singing their favourite songs.</title>
  </programme>
  <programme start="19-02-2024 01:00PM(00:30:00)" channel="DD Malayalam EPG Schedule &amp; Program Guide">
    <title>Varthakal- The host presents some of the latest news stories, current affairs and developments.</title>
  </programme>
  <programme start="19-02-2024 01:30PM(00:30:00)" channel="DD Malayalam EPG Schedule &amp; Program Guide">
    <title>Amrithabharatham- The host presents the latest updates and top news stories from across India.</title>
  </programme>
  <programme start="19-02-2024 02:00PM(01:00:00)" channel="DD Malayalam EPG Schedule &amp; Program Guide">
    <title>Doctor's Speak- Medical experts discuss various questions asked by people about COVID-19.</title>
  </programme>
  <programme start="19-02-2024 03:00PM(00:10:00)" channel="DD Malayalam EPG Schedule &amp; Program Guide">
    <title>Varthakal- The host presents some of the latest news stories, current affairs and developments.</title>
  </programme>
  <programme start="19-02-2024 03:10PM(00:25:00)" channel="DD Malayalam EPG Schedule &amp; Program Guide">
    <title>Kilivathil- Talented artists perform a compilation of songs composed by renowned singers.</title>
  </programme>
  <programme start="19-02-2024 03:35PM(00:25:00)" channel="DD Malayalam EPG Schedule &amp; Program Guide">
    <title>Classical Dance- Artists adept in the various forms of Indian classical dance perform an inspiring recital.</title>
  </programme>
  <programme start="19-02-2024 04:00PM(00:10:00)" channel="DD Malayalam EPG Schedule &amp; Program Guide">
    <title>Varthakal- The host presents some of the latest news stories, current affairs and developments.</title>
  </programme>
  <programme start="19-02-2024 04:10PM(00:50:00)" channel="DD Malayalam EPG Schedule &amp; Program Guide">
    <title>Koottinoru Pattu- The host talks to singers who sing their best songs and answer questions from the viewers.</title>
  </programme>
  <programme start="19-02-2024 05:00PM(00:15:00)" channel="DD Malayalam EPG Schedule &amp; Program Guide">
    <title>News Headlines- Nattu Varathakal: The presenter reports political and socio-economic news from India and around the world.</title>
  </programme>
  <programme start="19-02-2024 05:15PM(00:20:00)" channel="DD Malayalam EPG Schedule &amp; Program Guide">
    <title>Enswaram- Popular playback singers pay tribute to their teachers by singing their favourite songs.</title>
  </programme>
  <programme start="19-02-2024 05:35PM(00:25:00)" channel="DD Malayalam EPG Schedule &amp; Program Guide">
    <title>SIET- SIET introduces its activities and educational software for programming.</title>
  </programme>
  <programme start="19-02-2024 06:00PM(00:10:00)" channel="DD Malayalam EPG Schedule &amp; Program Guide">
    <title>Varthakal- The host presents some of the latest news stories, current affairs and developments.</title>
  </programme>
  <programme start="19-02-2024 06:10PM(00:30:00)" channel="DD Malayalam EPG Schedule &amp; Program Guide">
    <title>Krishidarshan- An expert gives advice on farming techniques and how to reap a good harvest.</title>
  </programme>
  <programme start="19-02-2024 06:40PM(00:20:00)" channel="DD Malayalam EPG Schedule &amp; Program Guide">
    <title>Best Of Chembai Music Festival- A look at some of the best performances that have taken place at Chembai Sangeetholsavam.</title>
  </programme>
  <programme start="19-02-2024 07:00PM(00:30:00)" channel="DD Malayalam EPG Schedule &amp; Program Guide">
    <title>Varthakal- The host presents some of the latest news stories, current affairs and developments.</title>
  </programme>
  <programme start="19-02-2024 07:30PM(01:00:00)" channel="DD Malayalam EPG Schedule &amp; Program Guide">
    <title>Samakalikam- The host sheds light on the latest political, sports, and entertainment updates.</title>
  </programme>
  <programme start="19-02-2024 08:30PM(00:30:00)" channel="DD Malayalam EPG Schedule &amp; Program Guide">
    <title>Om Namah Shivaya- The Hindu saga of Lord Shiva - Bolenath - Shankar and his consort Shakti/Parvati.</title>
  </programme>
  <programme start="19-02-2024 09:00PM(00:30:00)" channel="DD Malayalam EPG Schedule &amp; Program Guide">
    <title>Cherukolppuzha Hindu Matha Parishath- This program features the annual convention of Hindus held at Cherukolpuzha.</title>
  </programme>
  <programme start="19-02-2024 09:30PM(01:00:00)" channel="DD Malayalam EPG Schedule &amp; Program Guide">
    <title>Koottinoru Pattu- The host talks to singers who sing their best songs and answer questions from the viewers.</title>
  </programme>
  <programme start="19-02-2024 10:30PM(00:30:00)" channel="DD Malayalam EPG Schedule &amp; Program Guide">
    <title>Krishidarshan- An expert gives advice on farming techniques and how to reap a good harvest.</title>
  </programme>
  <programme start="19-02-2024 11:00PM(01:00:00)" channel="DD Malayalam EPG Schedule &amp; Program Guide">
    <title>Doctor's Speak- Medical experts discuss various questions asked by people about COVID-19.</title>
  </programme>
  <programme start="20-02-2024 12:00AM(01:00:00)" channel="DD Malayalam EPG Schedule &amp; Program Guide">
    <title>Samakalikam- The host sheds light on the latest political, sports, and entertainment updates.</title>
  </programme>
  <channel id="Kairali News EPG Schedule &amp; Program Guide">
    <display-name>Kairali News EPG Schedule &amp; Program Guide</display-name>
  </channel>
  <programme start="18-02-2024 12:30AM(00:30:00)" channel="Kairali News EPG Schedule &amp; Program Guide">
    <title>News N Views-</title>
  </programme>
  <programme start="18-02-2024 01:00AM(00:30:00)" channel="Kairali News EPG Schedule &amp; Program Guide">
    <title>News-</title>
  </programme>
  <programme start="18-02-2024 01:30AM(00:30:00)" channel="Kairali News EPG Schedule &amp; Program Guide">
    <title>News-</title>
  </programme>
  <programme start="18-02-2024 02:00AM(01:00:00)" channel="Kairali News EPG Schedule &amp; Program Guide">
    <title>News Night-</title>
  </programme>
  <programme start="18-02-2024 03:00AM(01:00:00)" channel="Kairali News EPG Schedule &amp; Program Guide">
    <title>9PM-</title>
  </programme>
  <programme start="18-02-2024 04:00AM(01:00:00)" channel="Kairali News EPG Schedule &amp; Program Guide">
    <title>News N Views-</title>
  </programme>
  <programme start="18-02-2024 05:00AM(00:30:00)" channel="Kairali News EPG Schedule &amp; Program Guide">
    <title>American Focus-</title>
  </programme>
  <programme start="18-02-2024 05:30AM(00:30:00)" channel="Kairali News EPG Schedule &amp; Program Guide">
    <title>News-</title>
  </programme>
  <programme start="18-02-2024 06:00AM(00:30:00)" channel="Kairali News EPG Schedule &amp; Program Guide">
    <title>First News-</title>
  </programme>
  <programme start="18-02-2024 06:30AM(00:30:00)" channel="Kairali News EPG Schedule &amp; Program Guide">
    <title>Pradeshika Varthakal-</title>
  </programme>
  <programme start="18-02-2024 07:00AM(01:30:00)" channel="Kairali News EPG Schedule &amp; Program Guide">
    <title>Good Morning Keralam-</title>
  </programme>
  <programme start="18-02-2024 08:30AM(00:30:00)" channel="Kairali News EPG Schedule &amp; Program Guide">
    <title>Speed News-</title>
  </programme>
  <programme start="18-02-2024 09:00AM(00:30:00)" channel="Kairali News EPG Schedule &amp; Program Guide">
    <title>Pradeshika Varthakal-</title>
  </programme>
  <programme start="18-02-2024 09:30AM(00:30:00)" channel="Kairali News EPG Schedule &amp; Program Guide">
    <title>Morning Round Up-</title>
  </programme>
  <programme start="18-02-2024 10:00AM(02:00:00)" channel="Kairali News EPG Schedule &amp; Program Guide">
    <title>News Time-</title>
  </programme>
  <programme start="18-02-2024 12:00PM(00:30:00)" channel="Kairali News EPG Schedule &amp; Program Guide">
    <title>Mid Day News-</title>
  </programme>
  <programme start="18-02-2024 12:30PM(00:30:00)" channel="Kairali News EPG Schedule &amp; Program Guide">
    <title>Speed News-</title>
  </programme>
  <programme start="18-02-2024 01:00PM(01:00:00)" channel="Kairali News EPG Schedule &amp; Program Guide">
    <title>Noon Round Up-</title>
  </programme>
  <programme start="18-02-2024 02:00PM(00:30:00)" channel="Kairali News EPG Schedule &amp; Program Guide">
    <title>News At 2 PM-</title>
  </programme>
  <programme start="18-02-2024 02:30PM(00:30:00)" channel="Kairali News EPG Schedule &amp; Program Guide">
    <title>Hello Doctor-</title>
  </programme>
  <programme start="18-02-2024 03:00PM(00:30:00)" channel="Kairali News EPG Schedule &amp; Program Guide">
    <title>Tea Time News-</title>
  </programme>
  <programme start="18-02-2024 03:30PM(00:30:00)" channel="Kairali News EPG Schedule &amp; Program Guide">
    <title>Tele Marketing-</title>
  </programme>
  <programme start="18-02-2024 04:00PM(00:30:00)" channel="Kairali News EPG Schedule &amp; Program Guide">
    <title>News At 4-</title>
  </programme>
  <programme start="18-02-2024 04:30PM(00:30:00)" channel="Kairali News EPG Schedule &amp; Program Guide">
    <title>Kairali Archiev's T-</title>
  </programme>
  <programme start="18-02-2024 05:00PM(00:30:00)" channel="Kairali News EPG Schedule &amp; Program Guide">
    <title>News At 5-</title>
  </programme>
  <programme start="18-02-2024 05:30PM(00:30:00)" channel="Kairali News EPG Schedule &amp; Program Guide">
    <title>Pradeshika Varthakal-</title>
  </programme>
  <programme start="18-02-2024 06:00PM(01:00:00)" channel="Kairali News EPG Schedule &amp; Program Guide">
    <title>Evening Round Up-</title>
  </programme>
  <programme start="18-02-2024 07:00PM(00:30:00)" channel="Kairali News EPG Schedule &amp; Program Guide">
    <title>News At 7-</title>
  </programme>
  <programme start="18-02-2024 07:30PM(00:30:00)" channel="Kairali News EPG Schedule &amp; Program Guide">
    <title>Todays Debate-</title>
  </programme>
  <programme start="18-02-2024 08:00PM(01:00:00)" channel="Kairali News EPG Schedule &amp; Program Guide">
    <title>News N Views-</title>
  </programme>
  <programme start="18-02-2024 09:00PM(00:30:00)" channel="Kairali News EPG Schedule &amp; Program Guide">
    <title>News At 9 PM-</title>
  </programme>
  <programme start="18-02-2024 09:30PM(00:30:00)" channel="Kairali News EPG Schedule &amp; Program Guide">
    <title>Speed News-</title>
  </programme>
  <programme start="18-02-2024 10:00PM(00:30:00)" channel="Kairali News EPG Schedule &amp; Program Guide">
    <title>News at 10-</title>
  </programme>
  <programme start="18-02-2024 10:30PM(00:30:00)" channel="Kairali News EPG Schedule &amp; Program Guide">
    <title>Pradeshika Varthakal-</title>
  </programme>
  <programme start="18-02-2024 11:00PM(01:00:00)" channel="Kairali News EPG Schedule &amp; Program Guide">
    <title>News Night-</title>
  </programme>
  <programme start="19-02-2024 12:00AM(00:30:00)" channel="Kairali News EPG Schedule &amp; Program Guide">
    <title>Gulf News-</title>
  </programme>
  <programme start="19-02-2024 12:30AM(00:30:00)" channel="Kairali News EPG Schedule &amp; Program Guide">
    <title>News N Views-</title>
  </programme>
  <programme start="19-02-2024 01:00AM(00:30:00)" channel="Kairali News EPG Schedule &amp; Program Guide">
    <title>News-</title>
  </programme>
  <programme start="19-02-2024 01:30AM(00:30:00)" channel="Kairali News EPG Schedule &amp; Program Guide">
    <title>News-</title>
  </programme>
  <programme start="19-02-2024 02:00AM(01:00:00)" channel="Kairali News EPG Schedule &amp; Program Guide">
    <title>News Night-</title>
  </programme>
  <programme start="19-02-2024 03:00AM(01:00:00)" channel="Kairali News EPG Schedule &amp; Program Guide">
    <title>9PM-</title>
  </programme>
  <programme start="19-02-2024 04:00AM(01:00:00)" channel="Kairali News EPG Schedule &amp; Program Guide">
    <title>News N Views-</title>
  </programme>
  <programme start="19-02-2024 05:00AM(00:30:00)" channel="Kairali News EPG Schedule &amp; Program Guide">
    <title>USA Weekly-</title>
  </programme>
  <programme start="19-02-2024 05:30AM(00:30:00)" channel="Kairali News EPG Schedule &amp; Program Guide">
    <title>News-</title>
  </programme>
  <programme start="19-02-2024 06:00AM(00:30:00)" channel="Kairali News EPG Schedule &amp; Program Guide">
    <title>First News-</title>
  </programme>
  <programme start="19-02-2024 06:30AM(00:30:00)" channel="Kairali News EPG Schedule &amp; Program Guide">
    <title>Pradeshika Varthakal-</title>
  </programme>
  <programme start="19-02-2024 07:00AM(01:30:00)" channel="Kairali News EPG Schedule &amp; Program Guide">
    <title>Good Morning Keralam-</title>
  </programme>
  <programme start="19-02-2024 08:30AM(00:30:00)" channel="Kairali News EPG Schedule &amp; Program Guide">
    <title>Speed News-</title>
  </programme>
  <programme start="19-02-2024 09:00AM(00:30:00)" channel="Kairali News EPG Schedule &amp; Program Guide">
    <title>Pradeshika Varthakal-</title>
  </programme>
  <programme start="19-02-2024 09:30AM(00:30:00)" channel="Kairali News EPG Schedule &amp; Program Guide">
    <title>Morning Round Up-</title>
  </programme>
  <programme start="19-02-2024 10:00AM(02:00:00)" channel="Kairali News EPG Schedule &amp; Program Guide">
    <title>News Time-</title>
  </programme>
  <programme start="19-02-2024 12:00PM(00:30:00)" channel="Kairali News EPG Schedule &amp; Program Guide">
    <title>Mid Day News-</title>
  </programme>
  <programme start="19-02-2024 12:30PM(00:30:00)" channel="Kairali News EPG Schedule &amp; Program Guide">
    <title>Speed News-</title>
  </programme>
  <programme start="19-02-2024 01:00PM(01:00:00)" channel="Kairali News EPG Schedule &amp; Program Guide">
    <title>Noon Round Up-</title>
  </programme>
  <programme start="19-02-2024 02:00PM(00:30:00)" channel="Kairali News EPG Schedule &amp; Program Guide">
    <title>News At 2 PM-</title>
  </programme>
  <programme start="19-02-2024 02:30PM(00:30:00)" channel="Kairali News EPG Schedule &amp; Program Guide">
    <title>Hello Doctor-</title>
  </programme>
  <programme start="19-02-2024 03:00PM(00:30:00)" channel="Kairali News EPG Schedule &amp; Program Guide">
    <title>Tea Time News-</title>
  </programme>
  <programme start="19-02-2024 03:30PM(00:30:00)" channel="Kairali News EPG Schedule &amp; Program Guide">
    <title>Tele Marketing-</title>
  </programme>
  <programme start="19-02-2024 04:00PM(00:30:00)" channel="Kairali News EPG Schedule &amp; Program Guide">
    <title>News At 4-</title>
  </programme>
  <programme start="19-02-2024 04:30PM(00:30:00)" channel="Kairali News EPG Schedule &amp; Program Guide">
    <title>American Focus-</title>
  </programme>
  <programme start="19-02-2024 05:00PM(00:30:00)" channel="Kairali News EPG Schedule &amp; Program Guide">
    <title>News At 5-</title>
  </programme>
  <programme start="19-02-2024 05:30PM(00:30:00)" channel="Kairali News EPG Schedule &amp; Program Guide">
    <title>Pradeshika Varthakal-</title>
  </programme>
  <programme start="19-02-2024 06:00PM(01:00:00)" channel="Kairali News EPG Schedule &amp; Program Guide">
    <title>Evening Round Up-</title>
  </programme>
  <programme start="19-02-2024 07:00PM(00:30:00)" channel="Kairali News EPG Schedule &amp; Program Guide">
    <title>News At 7-</title>
  </programme>
  <programme start="19-02-2024 07:30PM(00:30:00)" channel="Kairali News EPG Schedule &amp; Program Guide">
    <title>Todays Debate-</title>
  </programme>
  <programme start="19-02-2024 08:00PM(01:00:00)" channel="Kairali News EPG Schedule &amp; Program Guide">
    <title>News N Views-</title>
  </programme>
  <programme start="19-02-2024 09:00PM(00:30:00)" channel="Kairali News EPG Schedule &amp; Program Guide">
    <title>News At 9 PM-</title>
  </programme>
  <programme start="19-02-2024 09:30PM(00:30:00)" channel="Kairali News EPG Schedule &amp; Program Guide">
    <title>Speed News-</title>
  </programme>
  <programme start="19-02-2024 10:00PM(00:30:00)" channel="Kairali News EPG Schedule &amp; Program Guide">
    <title>News at 10-</title>
  </programme>
  <programme start="19-02-2024 10:30PM(00:30:00)" channel="Kairali News EPG Schedule &amp; Program Guide">
    <title>Pradeshika Varthakal-</title>
  </programme>
  <programme start="19-02-2024 11:00PM(01:00:00)" channel="Kairali News EPG Schedule &amp; Program Guide">
    <title>News Night-</title>
  </programme>
  <programme start="20-02-2024 12:00AM(00:30:00)" channel="Kairali News EPG Schedule &amp; Program Guide">
    <title>Gulf News-</title>
  </programme>
</tv>
